ricklib/__init__.py
ricklib/audio.py
ricklib/glib.py
ricklib/graphics2d.py
ricklib/pngenerator.py
ricklib/polynomial.py
ricklib-0.0.11.dist-info/METADATA
ricklib-0.0.11.dist-info/WHEEL
ricklib-0.0.11.dist-info/licenses/LICENSE
ricklib-0.0.11.dist-info/RECORD
