Metadata-Version: 2.3
Name: ricklib
Version: 0.0.11
Summary: A small package for personal use including useful operations.
Project-URL: Homepage, https://github.com/rick-howell/ricklib
Project-URL: Issues, https://github.com/rick-howell/ricklib/issues
Author-email: "Richard (Rick) Howell" <rick.howell.arts@gmail.com>
License: MIT License
License-File: LICENSE
Classifier: License :: OSI Approved :: MIT License
Classifier: Operating System :: OS Independent
Classifier: Programming Language :: Python :: 3
Requires-Python: >=3.8
